estimint/__init__.py
estimint/data_processing.py
estimint/globals.py
estimint/models.py
estimint/plotting.py
estimint/run.py
estimint/storage.py
estimint/train.py
estimint/utils.py
estimint/data/estiMINT_model.pkl
estimint/data/model_checksum.txt
estimint/data/models-checksums.csv
estimint/data/models-tag.txt
estimint-1.2.0.dist-info/METADATA
estimint-1.2.0.dist-info/WHEEL
estimint-1.2.0.dist-info/top_level.txt
estimint-1.2.0.dist-info/RECORD
