Metadata-Version: 2.4
Name: estimint
Version: 1.2.0
Summary: EIR Estimation using Machine learning INTerventions - Python port
Author-email: Cosmo Santoni <cosmo.santoni@imperial.ac.uk>
License-Expression: MIT
Project-URL: Homepage, https://github.com/CosmoNaught/estiMINT
Project-URL: Documentation, https://github.com/CosmoNaught/estiMINT#readme
Project-URL: Repository, https://github.com/CosmoNaught/estiMINT
Project-URL: Issues, https://github.com/CosmoNaught/estiMINT/issues
Keywords: malaria,EIR,machine-learning,xgboost,epidemiology
Classifier: Development Status :: 4 - Beta
Classifier: Intended Audience :: Science/Research
Classifier: Operating System :: OS Independent
Classifier: Programming Language :: Python :: 3
Classifier: Programming Language :: Python :: 3.9
Classifier: Programming Language :: Python :: 3.10
Classifier: Programming Language :: Python :: 3.11
Classifier: Programming Language :: Python :: 3.12
Classifier: Topic :: Scientific/Engineering :: Bio-Informatics
Requires-Python: >=3.9
Requires-Dist: numpy>=1.20.0
Requires-Dist: pandas>=1.3.0
Requires-Dist: duckdb>=0.8.0
Requires-Dist: xgboost>=1.6.0
Requires-Dist: scikit-learn>=1.0.0
Requires-Dist: matplotlib>=3.4.0
Provides-Extra: dev
Requires-Dist: pytest>=7.0.0; extra == "dev"
Requires-Dist: pytest-cov>=4.0.0; extra == "dev"
Requires-Dist: black>=23.0.0; extra == "dev"
Requires-Dist: isort>=5.12.0; extra == "dev"
Requires-Dist: mypy>=1.0.0; extra == "dev"
Requires-Dist: flake8>=6.0.0; extra == "dev"
Provides-Extra: download
Requires-Dist: requests>=2.28.0; extra == "download"
Requires-Dist: appdirs>=1.4.0; extra == "download"
